{
  "appId": "com.insightboard.ai",
  "productName": "本地AI看板",
  "directories": {
    "output": "dist-electron"
  },
  "files": [
    "dist/**/*",
    "electron/dist/**/*",
    "resources/**/*",
    "package.json"
  ],
  "extraMetadata": {
    "main": "electron/dist/main.js"
  },
  "win": {
    "signAndEditExecutable": false,
    "target": [
      {
        "target": "nsis",
        "arch": ["x64"]
      },
      {
        "target": "portable",
        "arch": ["x64"]
      }
    ],
    "icon": "resources/icon.ico",
    "publisherName": "InsightBoard"
  },
  "nsis": {
    "oneClick": false,
    "perMachine": false,
    "allowToChangeInstallationDirectory": true,
    "createDesktopShortcut": true,
    "createStartMenuShortcut": true
  },
  "portable": {
    "artifactName": "${productName}-${version}-portable.${ext}"
  }
}
